homegrowndhe/__init__.py
homegrowndhe/__main__.py
homegrowndhe/dhe.py
homegrowndhe/main.py
homegrowndhe/util.py
homegrowndhe-0.3.3.dist-info/METADATA
homegrowndhe-0.3.3.dist-info/WHEEL
homegrowndhe-0.3.3.dist-info/RECORD
