Metadata-Version: 2.1
Name: homegrowndhe
Version: 0.3.3
Summary: 
Author: DJ Stomp
Author-email: noreply@85457381+djstompzone@users.noreply.github.com
Requires-Python: >=3.10,<4.0
Classifier: Programming Language :: Python :: 3
Classifier: Programming Language :: Python :: 3.10
Classifier: Programming Language :: Python :: 3.11
Classifier: Programming Language :: Python :: 3.12
Requires-Dist: cryptography (>=43.0.0,<44.0.0)
Requires-Dist: poetry2conda (>=0.3.0,<0.4.0)
Requires-Dist: pycryptodomex (>=3.20.0,<4.0.0)
Requires-Dist: pytest (>=8.3.2,<9.0.0)
Requires-Dist: twine (>=5.1.1,<6.0.0)
